delay_sys/__init__.py
delay_sys/delayed_tf.py
delay_sys/py.typed
delay_sys-0.1.1.dist-info/METADATA
delay_sys-0.1.1.dist-info/WHEEL
delay_sys-0.1.1.dist-info/entry_points.txt
delay_sys-0.1.1.dist-info/licenses/LICENSE
delay_sys-0.1.1.dist-info/RECORD
