Metadata-Version: 2.4
Name: delay_sys
Version: 0.1.1
Summary: A Python library for discretizing continuous-time transfer functions with time delays
Project-URL: Homepage, https://github.com/jamestjsp/delay_sys
Project-URL: Repository, https://github.com/jamestjsp/delay_sys.git
Project-URL: Issues, https://github.com/jamestjsp/delay_sys/issues
Author-email: James J <jamestjsp@outlook.com>
License: MIT
License-File: LICENSE
Keywords: control,delay,discretization,signal-processing,transfer-function
Classifier: Development Status :: 4 - Beta
Classifier: Intended Audience :: Developers
Classifier: Intended Audience :: Science/Research
Classifier: License :: OSI Approved :: MIT License
Classifier: Programming Language :: Python :: 3
Classifier: Programming Language :: Python :: 3.8
Classifier: Programming Language :: Python :: 3.9
Classifier: Programming Language :: Python :: 3.10
Classifier: Programming Language :: Python :: 3.11
Classifier: Programming Language :: Python :: 3.12
Classifier: Programming Language :: Python :: 3.13
Classifier: Topic :: Scientific/Engineering
Classifier: Topic :: Software Development :: Libraries :: Python Modules
Requires-Python: >=3.8
Requires-Dist: control>=0.9.0
Requires-Dist: matplotlib>=3.0.0
Requires-Dist: numpy>=1.19.0
